__init__.py
__version__.py
djangoaddicts/__init__.py
djangoaddicts/signalcontrol/__init__.py
djangoaddicts/signalcontrol/admin.py
djangoaddicts/signalcontrol/apps.py
djangoaddicts/signalcontrol/decorators.py
djangoaddicts/signalcontrol/models.py
djangoaddicts/signalcontrol/migrations/0001_initial.py
djangoaddicts/signalcontrol/migrations/0002_auto_20200618_1611.py
djangoaddicts/signalcontrol/migrations/0003_alter_signalcontrol_id.py
djangoaddicts/signalcontrol/migrations/__init__.py
django_signalcontrol-0.1.2.dist-info/LICENSE
django_signalcontrol-0.1.2.dist-info/METADATA
django_signalcontrol-0.1.2.dist-info/WHEEL
django_signalcontrol-0.1.2.dist-info/top_level.txt
django_signalcontrol-0.1.2.dist-info/RECORD
